odoo/addons/purchase_order_line_qty_to_receive/README.rst
odoo/addons/purchase_order_line_qty_to_receive/__init__.py
odoo/addons/purchase_order_line_qty_to_receive/__manifest__.py
odoo/addons/purchase_order_line_qty_to_receive/i18n/es.po
odoo/addons/purchase_order_line_qty_to_receive/i18n/fr.po
odoo/addons/purchase_order_line_qty_to_receive/i18n/purchase_order_line_qty_to_receive.pot
odoo/addons/purchase_order_line_qty_to_receive/models/__init__.py
odoo/addons/purchase_order_line_qty_to_receive/models/purchase_order_line.py
odoo/addons/purchase_order_line_qty_to_receive/readme/CONTRIBUTORS.rst
odoo/addons/purchase_order_line_qty_to_receive/readme/DESCRIPTION.rst
odoo/addons/purchase_order_line_qty_to_receive/static/description/icon.png
odoo/addons/purchase_order_line_qty_to_receive/static/description/index.html
odoo/addons/purchase_order_line_qty_to_receive/tests/__init__.py
odoo/addons/purchase_order_line_qty_to_receive/tests/test_purchase_order_line_qty_to_receive.py
odoo/addons/purchase_order_line_qty_to_receive/views/purchase_order.xml
odoo_addon_purchase_order_line_qty_to_receive-15.0.1.0.0.7.dist-info/METADATA
odoo_addon_purchase_order_line_qty_to_receive-15.0.1.0.0.7.dist-info/WHEEL
odoo_addon_purchase_order_line_qty_to_receive-15.0.1.0.0.7.dist-info/top_level.txt
odoo_addon_purchase_order_line_qty_to_receive-15.0.1.0.0.7.dist-info/RECORD
